libname/MSArqAuth.py
libname/__init__.py
MSArqAuth-0.0.1.dist-info/METADATA
MSArqAuth-0.0.1.dist-info/WHEEL
MSArqAuth-0.0.1.dist-info/top_level.txt
MSArqAuth-0.0.1.dist-info/RECORD
